foldedtensor/_C.cpython-39-x86_64-linux-gnu.so
foldedtensor/__init__.py
foldedtensor/functions.cpp
scripts/benchmark.py
tests/conftest.py
tests/test_folded_tensor.py
tests/test_multiprocessing.py
foldedtensor-0.4.0.dist-info/METADATA
foldedtensor-0.4.0.dist-info/WHEEL
foldedtensor-0.4.0.dist-info/top_level.txt
foldedtensor-0.4.0.dist-info/RECORD
foldedtensor-0.4.0.dist-info/licenses/LICENSE
