Metadata-Version: 2.1
Name: foldedtensor
Version: 0.4.0
Summary: PyTorch extension for handling deeply nested sequences of variable length
Author-email: Perceval Wajsbürt <perceval.wajsburt@aphp.fr>
License: Copyright 2023 Assistance Publique - Hôpitaux de Paris
Project-URL: homepage, https://github.com/aphp/foldedtensor/
Project-URL: repository, https://github.com/aphp/foldedtensor/
Classifier: Development Status :: 4 - Beta
Classifier: Intended Audience :: Developers
Classifier: Intended Audience :: Education
Classifier: Intended Audience :: Science/Research
Classifier: License :: OSI Approved :: BSD License
Classifier: Programming Language :: Python :: 3.7
Classifier: Programming Language :: Python :: 3.8
Classifier: Programming Language :: Python :: 3.9
Classifier: Programming Language :: Python :: 3.10
Classifier: Programming Language :: Python :: 3.11
Classifier: Programming Language :: Python :: 3.12
Classifier: Programming Language :: Python :: 3.13
Classifier: Programming Language :: C++
Classifier: Topic :: Scientific/Engineering
Classifier: Topic :: Scientific/Engineering :: Mathematics
Classifier: Topic :: Scientific/Engineering :: Artificial Intelligence
Classifier: Topic :: Software Development
Classifier: Topic :: Software Development :: Libraries
Classifier: Topic :: Software Development :: Libraries :: Python Modules
Requires-Python: <4.0,>=3.7.1
License-File: LICENSE
Requires-Dist: torch >1.0.0
Requires-Dist: numpy
Provides-Extra: dev
Requires-Dist: black ==22.6.0 ; extra == 'dev'
Requires-Dist: pre-commit >=2.18 ; extra == 'dev'
Requires-Dist: pytest ==7.1.1 ; extra == 'dev'
Requires-Dist: pytest-cov ==3.0.0 ; extra == 'dev'
